torchswarm/__init__.py
torchswarm/functions/__init__.py
torchswarm/particle/__init__.py
torchswarm/particle/particle_factory.py
torchswarm/swarmoptimizer/__init__.py
torchswarm/utils/__init__.py
torchswarm/utils/parameters.py
torchswarm/utils/rotation_utils.py
torchswarm-0.0.1.dist-info/LICENSE
torchswarm-0.0.1.dist-info/METADATA
torchswarm-0.0.1.dist-info/WHEEL
torchswarm-0.0.1.dist-info/top_level.txt
torchswarm-0.0.1.dist-info/RECORD
