Metadata-Version: 2.1
Name: torchswarm
Version: 0.0.1
Summary: A fast implementation of Particle Swarm Optimization using PyTorch
Home-page: https://github.com/rohanmohapatra/torchswarm
Author: Rohan Mohapatra
License: MIT
Platform: UNKNOWN
Classifier: Programming Language :: Python :: 3
Classifier: License :: OSI Approved :: MIT License
Classifier: Operating System :: OS Independent
Requires-Python: >=3.6
Requires-Dist: torch
